simplePatchManager/__init__.py
simplePatchManager/__main__.py
simplePatchManager/apply.py
simplePatchManager/command.py
simplePatchManager/create.py
simplePatchManager/edit.py
simplePatchManager/info.py
simplePatchManager/isapplied.py
simplePatchManager/list.py
simplePatchManager/remove.py
simplePatchManager/rename.py
simplePatchManager/status.py
simplePatchManager/view.py
simplePatchManager-0.0.2.dist-info/LICENSE
simplePatchManager-0.0.2.dist-info/METADATA
simplePatchManager-0.0.2.dist-info/WHEEL
simplePatchManager-0.0.2.dist-info/entry_points.txt
simplePatchManager-0.0.2.dist-info/top_level.txt
simplePatchManager-0.0.2.dist-info/RECORD
