Metadata-Version: 2.1
Name: simplePatchManager
Version: 0.0.2
Summary: Simple Patch Manager
Home-page: https://bitbucket.org/rmonico/simplePatchManager
Author: Rafael Monico
Author-email: rmonico1@gmail.com
License: GPL3
License-File: LICENSE
